Metadata-Version: 2.1
Name: pygseguro
Version: 0.1
Summary: Módulo para integrar com API do Pagseguro versão 3
Home-page: https://github.com/renzon/pygsegur
Author: Renzo Nuccitelli
Author-email: renzo@python.pro.br
License:                     GNU AFFERO GENERAL PUBLIC LICENSE
